LICENSE
pyscora_wrangler/__init__.py
pyscora_wrangler/aws/README.md
pyscora_wrangler/aws/__init__.py
pyscora_wrangler/aws/athena/__init__.py
pyscora_wrangler/aws/cognito/__init__.py
pyscora_wrangler/aws/constants.py
pyscora_wrangler/aws/dynamodb/__init__.py
pyscora_wrangler/aws/secretsmanager/__init__.py
pyscora_wrangler/aws/utils.py
pyscora_wrangler/constants.py
pyscora_wrangler/ldap/README.md
pyscora_wrangler/ldap/__init__.py
pyscora_wrangler/ldap/service/__init__.py
pyscora_wrangler/ldap/utils.py
pyscora_wrangler/utils.py
pyscora_wrangler-1.2.2.dist-info/LICENSE
pyscora_wrangler-1.2.2.dist-info/METADATA
pyscora_wrangler-1.2.2.dist-info/WHEEL
pyscora_wrangler-1.2.2.dist-info/RECORD
